dlogz/__init__.py
dlogz/__main__.py
dlogz/client.py
dlogz-0.0.5.dist-info/LICENSE
dlogz-0.0.5.dist-info/METADATA
dlogz-0.0.5.dist-info/WHEEL
dlogz-0.0.5.dist-info/entry_points.txt
dlogz-0.0.5.dist-info/top_level.txt
dlogz-0.0.5.dist-info/RECORD
