Metadata-Version: 2.1
Name: dlogz
Version: 0.0.5
Summary: package to ship dlogz
Author-email: m4st3rm1nd <tech@dlogz.com>
License: MIT License
Project-URL: Homepage, https://github.com/abhijeetkr93/dlogz_sdk
Keywords: dlogz
Classifier: License :: OSI Approved :: MIT License
Classifier: Programming Language :: Python
Classifier: Programming Language :: Python :: 3
Requires-Python: >=3.8
License-File: LICENSE
Provides-Extra: dev
Requires-Dist: black ; extra == 'dev'
